[
  {
    "frame": 0,
    "vel": 0,
    "modus": "wheel"
  },
  {
    "frame": 1,
    "vel": 0,
    "modus": "wheel"
  },
  {
    "frame": 2,
    "vel": 0,
    "modus": "wheel"
  },
  {
    "frame": 3,
    "vel": 0,
    "modus": "wheel"
  },
  {
    "frame": 4,
    "vel": 0,
    "modus": "wheel"
  },
  {
    "frame": 5,
    "vel": 0,
    "modus": "wheel"
  },
  {
    "frame": 6,
    "vel": 0,
    "modus": "wheel"
  },
  {
    "frame": 7,
    "vel": 0,
    "modus": "wheel"
  },
  {
    "frame": 8,
    "vel": 0,
    "modus": "wheel"
  },
  {
    "frame": 9,
    "vel": 0,
    "modus": "wheel"
  },
  {
    "frame": 10,
    "vel": 0,
    "modus": "wheel"
  },
  {
    "frame": 11,
    "vel": 0,
    "modus": "wheel"
  },
  {
    "frame": 12,
    "vel": 0,
    "modus": "wheel"
  },
  {
    "frame": 13,
    "vel": 0,
    "modus": "wheel"
  },
  {
    "frame": 14,
    "vel": 0,
    "modus": "wheel"
  },
  {
    "frame": 15,
    "vel": 0,
    "modus": "wheel"
  },
  {
    "frame": 16,
    "vel": 0,
    "modus": "wheel"
  },
  {
    "frame": 17,
    "vel": 0,
    "modus": "wheel"
  },
  {
    "frame": 18,
    "vel": 0,
    "modus": "wheel"
  },
  {
    "frame": 19,
    "vel": 0,
    "modus": "wheel"
  },
  {
    "frame": 20,
    "vel": 0,
    "modus": "wheel"
  },
  {
    "frame": 21,
    "vel": 0,
    "modus": "wheel"
  },
  {
    "frame": 22,
    "vel": 0,
    "modus": "wheel"
  },
  {
    "frame": 23,
    "vel": 0,
    "modus": "wheel"
  },
  {
    "frame": 24,
    "vel": 0,
    "modus": "wheel"
  },
  {
    "frame": 25,
    "vel": 0,
    "modus": "wheel"
  },
  {
    "frame": 26,
    "vel": 0,
    "modus": "wheel"
  },
  {
    "frame": 27,
    "vel": 0,
    "modus": "wheel"
  }
]